server_app/__init__.py
server_app/server_app.py
server_app/common/__init__.py
server_app/common/constants.py
server_app/common/decos.py
server_app/common/descriptors.py
server_app/common/errors.py
server_app/common/metaclasses.py
server_app/common/utils.py
server_app/doc/__init__.py
server_app/loging/__init__.py
server_app/loging/server_conf_log.py
server_app/server/__init__.py
server_app/server/add_user.py
server_app/server/config_window.py
server_app/server/core.py
server_app/server/main_window.py
server_app/server/remove_user.py
server_app/server/server_database.py
server_app/server/stat_window.py
server_pyqt_chat_June_Araym51-0.0.1.dist-info/METADATA
server_pyqt_chat_June_Araym51-0.0.1.dist-info/WHEEL
server_pyqt_chat_June_Araym51-0.0.1.dist-info/top_level.txt
server_pyqt_chat_June_Araym51-0.0.1.dist-info/RECORD
